flask_session/__init__.py
flask_session/sessions.py
flask_session2-1.3.0.dist-info/LICENSE
flask_session2-1.3.0.dist-info/WHEEL
flask_session2-1.3.0.dist-info/METADATA
flask_session2-1.3.0.dist-info/RECORD
