Metadata-Version: 2.1
Name: flask-session2
Version: 1.3.0
Summary: Adds server-side session support to your Flask application
License: BSD
Author: Shipeng Feng
Author-email: fsp261@gmail.com
Maintainer: Christopher Pickering
Requires-Python: >=3.7.2,<4.0.0
Classifier: Environment :: Web Environment
Classifier: Intended Audience :: Developers
Classifier: License :: OSI Approved :: BSD License
Classifier: License :: Other/Proprietary License
Classifier: Operating System :: OS Independent
Classifier: Programming Language :: Python :: 2
Classifier: Programming Language :: Python :: 3
Classifier: Programming Language :: Python :: 3.10
Classifier: Programming Language :: Python :: 3.8
Classifier: Programming Language :: Python :: 3.9
Classifier: Topic :: Internet :: WWW/HTTP :: Dynamic Content
Classifier: Topic :: Software Development :: Libraries :: Python Modules
Requires-Dist: Flask (>=2.2.2,<3.0.0)
Requires-Dist: cachelib (>=0.9.0,<0.10.0)
Requires-Dist: pytz (>=2022.2.1,<2023.0.0)
